Metadata-Version: 2.1
Name: spotify-videos
Version: 1.8
Summary: Simple tool to show Youtube music videos and lyrics for the playing Spotify songs
Home-page: https://github.com/marioortizmanero/spotify-music-videos
Author: Mario O.M.
Author-email: marioortizmanero@gmail.com
License: MIT
Keywords: spotify music video videos lyrics
Platform: UNKNOWN
Classifier: Development Status :: 5 - Production/Stable
Classifier: Intended Audience :: End Users/Desktop
Classifier: Topic :: Multimedia :: Sound/Audio :: Players
Classifier: License :: OSI Approved :: MIT License
Classifier: Programming Language :: Python :: 3
Classifier: Programming Language :: Python :: 3.6
Classifier: Programming Language :: Python :: 3.7
Requires-Python: >=3.6
Requires-Dist: youtube-dl
Requires-Dist: python-vlc
Requires-Dist: lyricwikia
Requires-Dist: requests (>=2.3.0)
Requires-Dist: six (>=1.10.0)
Requires-Dist: pydbus
